pytql/__init__.py
pytql/colors.py
pytql/data.py
pytql/data_converter.py
pytql/exceptions.py
pytql/table.py
pytql-0.0.3.dist-info/METADATA
pytql-0.0.3.dist-info/WHEEL
pytql-0.0.3.dist-info/top_level.txt
pytql-0.0.3.dist-info/RECORD
