Metadata-Version: 2.1
Name: pytql
Version: 0.0.3
Summary: Python Table Data Type with some SQL-like operations.
Home-page: https://github.com/Attakay78/Pytql
Author: AT_Khay (Richard Quaicoe)
Author-email: <richardquaicoe78@gmail.com>
License: UNKNOWN
Keywords: python,table,sql,query,filter
Platform: UNKNOWN
Classifier: Development Status :: 1 - Planning
Classifier: Intended Audience :: Developers
Classifier: Programming Language :: Python :: 3
Classifier: Operating System :: Unix
Classifier: Operating System :: MacOS :: MacOS X
Classifier: Operating System :: Microsoft :: Windows
